README.md
setup.py
lens/__init__.py
lens/args.py
lens/exceptions.py
lens/keys.py
lens/module.py
lens/pp.py
lens/runner.py
lens/parsers/__init__.py
lens/parsers/base.py
lens/parsers/json.py
lens/parsers/xml.py
lens_cli.egg-info/PKG-INFO
lens_cli.egg-info/SOURCES.txt
lens_cli.egg-info/dependency_links.txt
lens_cli.egg-info/entry_points.txt
lens_cli.egg-info/requires.txt
lens_cli.egg-info/top_level.txt