Metadata-Version: 2.1
Name: lens-cli
Version: 0.1.4
Summary: Extensible data structure traversal in the command line
Home-page: https://github.com/port-zero/lens
Author: Veit Heller
License: MIT
Download-URL: https://github.com/port-zero/lens/tarball/0.1.4
Platform: UNKNOWN
